cprint/__init__.py
cprint/cprint.py
c_print-1.0.1.dist-info/LICENSE
c_print-1.0.1.dist-info/METADATA
c_print-1.0.1.dist-info/WHEEL
c_print-1.0.1.dist-info/top_level.txt
c_print-1.0.1.dist-info/RECORD
