Metadata-Version: 2.1
Name: c-print
Version: 1.0.1
Summary: Small python package for printing text in different colours and typography.
Home-page: https://github.com/SimonPfeifer/cprint
Author: Simon Pfeifer
Author-email: s.pfeifer@2012.ljmu.ac.uk
License: UNKNOWN
Platform: UNKNOWN
